a2i/__init__.py
a2i/a2irp.py
a2i/a2irptest.py
amazon_textract_response_parser-1.0.2.data/scripts/amazon-textract-pipeline
trp/__init__.py
trp/t_pipeline.py
trp/t_tables.py
trp/trp2.py
trp/trp2_analyzeid.py
trp/trp2_expense.py
trp/trp2_lending.py
amazon_textract_response_parser-1.0.2.dist-info/METADATA
amazon_textract_response_parser-1.0.2.dist-info/WHEEL
amazon_textract_response_parser-1.0.2.dist-info/top_level.txt
amazon_textract_response_parser-1.0.2.dist-info/RECORD
