Metadata-Version: 2.1
Name: amazon-textract-response-parser
Version: 1.0.2
Summary: Easily parse JSON returned by Amazon Textract.
Home-page: https://github.com/aws-samples/amazon-textract-response-parser
Author: Amazon Rekognition Textract Demoes
Author-email: rekognition-textract-demos@amazon.com
License: Apache License Version 2.0
Keywords: amazon-textract-response-parser trp aws amazon textract ocr response parser
Platform: UNKNOWN
Classifier: Development Status :: 4 - Beta
Classifier: Topic :: Utilities
Classifier: License :: OSI Approved :: Apache Software License
Classifier: Programming Language :: Python :: 3.8
Classifier: Programming Language :: Python :: 3.9
Classifier: Programming Language :: Python :: 3.10
Classifier: Programming Language :: Python :: 3.11
Requires-Python: >=3.8
Requires-Dist: boto3
Requires-Dist: marshmallow (<4,>=3.14)
